bwa/__init__.py
bwa/discord.py
bwa/gmail.py
bwa/slack.py
bwa/telegm.py
bwa/test/__init__.py
bwa/test/test_discord.py
bwa/test/test_gmail.py
bwa/test/test_slack.py
bwa/test/test_telegram.py
bwa-1.1.1.dist-info/LICENSE
bwa-1.1.1.dist-info/METADATA
bwa-1.1.1.dist-info/WHEEL
bwa-1.1.1.dist-info/top_level.txt
bwa-1.1.1.dist-info/RECORD
