Metadata-Version: 2.1
Name: bwa
Version: 1.1.1
Summary: Bwa: Simple Notification Sender(Discord, Slack, Gmail and Telegram)
Home-page: https://github.com/somniumism/bwa
Author: SeungMin Lee(@somniumism)
Author-email: lsm.somniator@gmail.com
License: UNKNOWN
Keywords: notification-sender,discord,slack,telegram,gmail
Platform: UNKNOWN
Classifier: Programming Language :: Python :: 3.6
Classifier: License :: OSI Approved :: MIT License
Requires-Python: >=3.6
Requires-Dist: python-telegram-bot
Requires-Dist: requests
Requires-Dist: yagmail (>=0.11.214)
